<?xml version="1.0" encoding="utf-8"?>
<install type="acesef_ext" version="1.5.0" method="upgrade">
	<name>Contact</name>
	<author>JoomAce LLC</author>
	<creationDate>June 2011</creationDate>
	<copyright>(C) 2009-2011 JoomAce LLC</copyright>
	<license>GNU/GPL http://www.gnu.org/copyleft/gpl.html</license>
	<authorEmail>info@joomace.net</authorEmail>
	<authorUrl>www.joomace.net</authorUrl>
	<version>1.5.3</version>
	<description>Contact extension for AceSEF.</description>
	<files>
		<filename acesef_ext="com_contact">com_contact.php</filename>
	</files>
	<install>
		<defaultParams>
			<defaultParam name="skip_menu" value="1" />
		</defaultParams>
	</install>
	<params group="url">
		<param name="contact_part" type="list" default="global" label="ACESEF_PARAMS_CONTACT_PART_CONTACT" description="ACESEF_PARAMS_CONTACT_PART_CONTACT">
 			<option value="global">Use Global</option>
 			<option value="title">ACESEF_COMMON_TITLE_FIELD</option>
 			<option value="alias">ACESEF_COMMON_ALIAS_FIELD</option>
 		</param>
		<param name="category_part" type="list" default="global" label="ACESEF_PARAMS_URL_PART_CATEGORY" description="ACESEF_PARAMS_URL_PART_CATEGORY">
 			<option value="global">Use Global</option>
 			<option value="title">ACESEF_COMMON_TITLE_FIELD</option>
 			<option value="alias">ACESEF_COMMON_ALIAS_FIELD</option>
 		</param>
		<param type="spacer" default="&lt;hr/&gt;" />
		<param name="contactid_inc" type="radio" default="1" label="ACESEF_PARAMS_CONTACT_CONTACT_ID" description="ACESEF_PARAMS_CONTACT_CONTACT_ID_HELP">
 			<option value="1">No</option>
 			<option value="2">Yes</option>
 		</param>
		<param name="category_inc" type="list" default="1" label="ACESEF_PARAMS_URL_CATEGORY" description="ACESEF_PARAMS_URL_CATEGORY_HELP">
 			<option value="1">No</option>
 			<option value="2">ACESEF_PARAMS_URL_CATEGORY_LAST</option>
 			<option value="3">ACESEF_PARAMS_URL_CATEGORY_ALL</option>
 		</param>
 		<param name="categoryid_inc" type="radio" default="1" label="ACESEF_PARAMS_URL_CATEGORY_ID" description="ACESEF_PARAMS_URL_CATEGORY_ID_HELP">
 			<option value="1">No</option>
 			<option value="2">Yes</option>
 		</param>
	</params>
	<params group="categorylist">
 		<param name="categorylist" type="text" label="" description=""/>
	</params>
</install>