<?xml version="1.0" encoding="utf-8"?>
<metadata>
	<layout title="URL">
		<message>
			<![CDATA[This layout will add the selected AceSEF URL to menu to prevent duplicated URLs coused by different ItemIDs.]]>
		</message>
	</layout>
    <fields name="request">
		<fieldset name="request" addfieldpath="/administrator/components/com_acesef/library/elements">
			<field name="id"
				type="urls"
				description="Select any URL that has been generated by AceSEF."
				label="Select URL"
				required="true"
			/>
		</fieldset>
	</fields>
	<state>
		<name>URL</name>
		<description>This layout will add the selected AceSEF URL to menu to prevent duplicated URLs coused by different ItemIDs.</description>
		<url addpath="/administrator/components/com_acesef/library/elements">
			<param name="id" type="urls" size="5" default="" label="Select URL" description="Select any URL that has been generated by AceSEF." />
		</url>
	</state>
</metadata>
